apcIpmiMonitor/Command.py
apcIpmiMonitor/Config.py
apcIpmiMonitor/__init__.py
apcIpmiMonitor/__main__.py
apcIpmiMonitor/Domain/Server.py
apcIpmiMonitor/Domain/__init__.py
apcIpmiMonitor/Formatter/ServerStatusFormatter.py
apcIpmiMonitor/Formatter/__init__.py
apcIpmiMonitor/Infrastructure/ApcGateway.py
apcIpmiMonitor/Infrastructure/IpmiGateway.py
apcIpmiMonitor/Infrastructure/__init__.py
test/__init__.py
test/conftest.py
apc_ipmi_monitor_ericbo-0.1.1.dist-info/METADATA
apc_ipmi_monitor_ericbo-0.1.1.dist-info/WHEEL
apc_ipmi_monitor_ericbo-0.1.1.dist-info/entry_points.txt
apc_ipmi_monitor_ericbo-0.1.1.dist-info/top_level.txt
apc_ipmi_monitor_ericbo-0.1.1.dist-info/RECORD
