Metadata-Version: 2.1
Name: apc-ipmi-monitor-ericbo
Version: 0.1.1
Summary: Trigger a graceful shutdown on all servers in the event there is an extended power outage.
Home-page: https://github.com/ericbo/apc-ipmi-monitor
Author: Eric Bottazzi
Author-email: author@example.com
License: UNKNOWN
Platform: UNKNOWN
Classifier: Programming Language :: Python :: 3
Classifier: License :: OSI Approved :: Mozilla Public License 2.0 (MPL 2.0)
Classifier: Operating System :: POSIX :: Linux
Requires-Python: >=3.6
